{"uuids": {"phone_id": "6f43121d-4a36-4509-91cc-8bb469be59d3", "uuid": "74cad30a-b9a7-4e5d-83ff-a7dbd91ec1db", "client_session_id": "c0f332c1-20d1-494e-9486-efb811e99361", "advertising_id": "cca741d3-f652-4f44-9ee2-54b382cd27e3", "device_id": "android-fa9bcb28d8c40469"}, "cookie": {"csrftoken": "2cINHC55pAHOER0D2Xk7ljayKYJUYLm4", "ds_user": "lapalmerafc", "ds_user_id": "44718599386", "ig_direct_region_hint": "ATN", "mid": "YCQxHAABAAGy704uAoea8IsXuwJ-", "rur": "ATN", "sessionid": "44718599386%3AoULO56yqnobuy7%3A26", "shbid": "17843", "shbts": "1612984608.3671246"}, "timing_value": {"last_login": 1612984607.899384, "last_experiments": 1612984607.9003818}, "device_settings": {"app_version": "117.0.0.28.123", "android_version": "28", "android_release": "9.0", "dpi": "420dpi", "resolution": "1080x1920", "manufacturer": "OnePlus", "device": "ONEPLUS A3003", "model": "OnePlus3", "cpu": "qcom", "version_code": "180322800"}, "user_agent": "Instagram 117.0.0.28.123 Android (28/9.0; 420dpi; 1080x1920; OnePlus; ONEPLUS A3003; OnePlus3; qcom; en_US; 180322800)"}